LICENSE.txt
README.md
setup.cfg
setup.py
jgmd/__init__.py
jgmd.egg-info/PKG-INFO
jgmd.egg-info/SOURCES.txt
jgmd.egg-info/dependency_links.txt
jgmd.egg-info/requires.txt
jgmd.egg-info/top_level.txt
jgmd/events/__init__.py
jgmd/events/eventEmitter.py
jgmd/logging/__init__.py
jgmd/logging/loggingConsts.py
jgmd/logging/loggingUtil.py
jgmd/logging/interfaces/__init__.py
jgmd/logging/interfaces/freeTextLogger.py
jgmd/logging/interfaces/logger.py
jgmd/logging/interfaces/tableLogger.py
jgmd/logging/lazyLogging/__init__.py
jgmd/logging/lazyLogging/consts.py
jgmd/logging/lazyLogging/lazyLogBuffer.py
jgmd/logging/lazyLogging/logEntry.py
jgmd/util/__init__.py
jgmd/util/appUtil.py
jgmd/util/envUtil.py
jgmd/util/errorUtil.py
jgmd/util/fileUtil.py
jgmd/util/timeUtil.py