Metadata-Version: 2.1
Name: jgmd
Version: 4.0.9
Summary: A general-purpose python package for logging, event-emission, and other common code.
Home-page: https://github.com/jonathangardnermd/jgmd
Download-URL: https://github.com/jonathangardnermd/jgmd/archive/refs/tags/v4.0.9.tar.gz
Author: Jonathan Gardner
Author-email: jonathangardnermd@outlook.com
License: MIT
Keywords: PYTHON,LOGGING,EVENTS,UTILITY
Classifier: Development Status :: 3 - Alpha
Classifier: Intended Audience :: Developers
Classifier: Topic :: Software Development :: Build Tools
Classifier: License :: OSI Approved :: MIT License
Classifier: Programming Language :: Python :: 3.13
License-File: LICENSE.txt
Requires-Dist: tabulate
Requires-Dist: python-dotenv
Requires-Dist: pydantic
